console/__init__.py
console/console.py
console/printer.py
roma_console-1.0.3.dist-info/LICENSE
roma_console-1.0.3.dist-info/METADATA
roma_console-1.0.3.dist-info/WHEEL
roma_console-1.0.3.dist-info/top_level.txt
roma_console-1.0.3.dist-info/RECORD
