Metadata-Version: 2.1
Name: roma-console
Version: 1.0.3
Summary: Utilities for print fancy text in terminal.
Home-page: https://github.com/WilliamRo/console
Author: William Ro
Author-email: willi4m@zju.edu.cn
License: Apache-2.0
Download-URL: https://github.com/WilliamRo/console/tarball/v1.0.3
Keywords: console,terminal,color
Platform: UNKNOWN
Classifier: Development Status :: 5 - Production/Stable
Classifier: Environment :: Console
Classifier: Intended Audience :: Developers
Classifier: Intended Audience :: Other Audience
Classifier: License :: OSI Approved :: Apache Software License
Classifier: Natural Language :: English
Classifier: Operating System :: OS Independent
Classifier: Programming Language :: Python :: 2
Classifier: Programming Language :: Python :: 3
Classifier: Topic :: Artistic Software
Classifier: Topic :: Printing
Classifier: Topic :: Utilities
